fm_nbn/__init__.py
fm_nbn/core.py
fm_nbn-0.2.dist-info/METADATA
fm_nbn-0.2.dist-info/WHEEL
fm_nbn-0.2.dist-info/top_level.txt
fm_nbn-0.2.dist-info/RECORD
