Metadata-Version: 2.4
Name: fm_nbn
Version: 0.2
Summary: A simple folder manipulation utility library
Author: NB Ngọc
Author-email: nbngoc.udu.ptit@email.com
Requires-Python: >=3.6
Dynamic: author
Dynamic: author-email
Dynamic: requires-python
Dynamic: summary
